ldmudinteractives/__init__.py
ldmudinteractives/control.py
ldmudinteractives/input.py
ldmudinteractives/interactive.py
ldmudinteractives/message.py
ldmudinteractives/ob.py
ldmudinteractives/stack.py
ldmudinteractives/util.py
ldmud_efun_virtual_interactives-0.0.2.dist-info/METADATA
ldmud_efun_virtual_interactives-0.0.2.dist-info/WHEEL
ldmud_efun_virtual_interactives-0.0.2.dist-info/entry_points.txt
ldmud_efun_virtual_interactives-0.0.2.dist-info/top_level.txt
ldmud_efun_virtual_interactives-0.0.2.dist-info/RECORD
